pesepay/__init__.py
pesepay/payments.py
pesepay/pesepay.py
pesepay/response.py
pesepay-1.0.8.dist-info/LICENSE
pesepay-1.0.8.dist-info/METADATA
pesepay-1.0.8.dist-info/WHEEL
pesepay-1.0.8.dist-info/top_level.txt
pesepay-1.0.8.dist-info/RECORD
