Metadata-Version: 2.1
Name: pesepay
Version: 1.0.8
Summary: Pesepay online payment gateway integration
Home-page: UNKNOWN
Author: CodeVirtus
Author-email: developer@codevirtus.com
License: UNKNOWN
Keywords: pesepay
Platform: UNKNOWN
Classifier: Development Status :: 1 - Planning
Classifier: Intended Audience :: Developers
Classifier: Programming Language :: Python :: 3
Classifier: Operating System :: Unix
Classifier: Operating System :: MacOS :: MacOS X
Classifier: Operating System :: Microsoft :: Windows
